Metadata-Version: 2.1
Name: typegenie-test-version
Version: 0.1.5
Summary: Client Library for TypeGenie API. Check out https://api.typegenie.net for more info.
Home-page: https://github.com/abhitopia/TypeGenieApiClient
Author: abhitopia
Author-email: hi@typegenie.net
License: UNKNOWN
Platform: UNKNOWN
Classifier: License :: OSI Approved :: MIT License
Classifier: Operating System :: OS Independent
Classifier: Programming Language :: Python :: 3
